harmonization/elastic_net.py
harmonization/config.py
harmonization/solver.py
harmonization/_glmnet.cpython-313-darwin.so
harmonization/__init__.py
harmonization/scripts.py
harmonization/dictionary.py
harmonization/recon.py
harmonization/tests/test_config.py
harmonization/tests/test_scripts.py
harmonization/tests/datasets_bids/config_bids.yaml
harmonization/tests/datasets_bids/config_upscale_bids.yaml
harmonization/tests/datasets_bids/subj2-bids/dwi/subj2-dwi.nii.gz
harmonization/tests/datasets_bids/subj2-bids/dwi/subj2-dwi.bvecs
harmonization/tests/datasets_bids/subj2-bids/dwi/subj2-dwi.bvals
harmonization/tests/datasets_bids/subj2-bids/dwi/subj2-dwi_brain_mask.nii.gz
harmonization/tests/datasets_bids/subj1-bids/dwi/subj1-dwi_brain_mask.nii.gz
harmonization/tests/datasets_bids/subj1-bids/dwi/subj1-dwi.bvals
harmonization/tests/datasets_bids/subj1-bids/dwi/subj1-dwi.nii.gz
harmonization/tests/datasets_bids/subj1-bids/dwi/subj1-dwi.bvecs
harmonization/tests/datasets/config_upscale.yaml
harmonization/tests/datasets/config.yaml
harmonization/tests/datasets/subj1/dwi_brain_mask.nii.gz
harmonization/tests/datasets/subj1/dwi.bvals
harmonization/tests/datasets/subj1/dwi.nii.gz
harmonization/tests/datasets/subj1/dwi.bvecs
harmonization/tests/datasets/subj2/dwi_brain_mask.nii.gz
harmonization/tests/datasets/subj2/dwi.bvals
harmonization/tests/datasets/subj2/dwi.nii.gz
harmonization/tests/datasets/subj2/dwi.bvecs
harmonization/.dylibs/libgfortran.5.dylib
harmonization/.dylibs/libquadmath.0.dylib
harmonization/.dylibs/libgcc_s.1.1.dylib
dmri_harmonization-0.2.dist-info/RECORD
dmri_harmonization-0.2.dist-info/WHEEL
dmri_harmonization-0.2.dist-info/entry_points.txt
dmri_harmonization-0.2.dist-info/METADATA
