Metadata-Version: 2.1
Name: dmri-harmonization
Version: 0.2
Summary: Implementation of "Harmonization of diffusion MRI datasets with adaptive dictionary learning".
Author: Samuel St-Jean
License: GPLv2
Project-URL: homepage, https://github.com/samuelstjean/harmonization
Project-URL: changelog, https://github.com/samuelstjean/harmonization/blob/master/CHANGELOG.md
Requires-Python: >=3.9
Requires-Dist: numpy>=1.23
Requires-Dist: scipy>=1.8
Requires-Dist: pyyaml>=5.1
Requires-Dist: nibabel>=2.4
Requires-Dist: scikit-learn>=0.21
Requires-Dist: joblib>=1.3
Requires-Dist: tqdm>=4.32.2
Requires-Dist: nlsam>=0.7
Requires-Dist: autodmri>=0.2.7
